email_operations/__init__.py
email_operations/email.cfg
email_operations/email_operations.py
email_operations/outLook_operations.py
email_operations-0.0.2.dist-info/LICENSE.txt
email_operations-0.0.2.dist-info/METADATA
email_operations-0.0.2.dist-info/WHEEL
email_operations-0.0.2.dist-info/top_level.txt
email_operations-0.0.2.dist-info/RECORD
