Metadata-Version: 2.1
Name: email-operations
Version: 0.0.2
Summary: Short description
Home-page: https://gitee.com/SkyOceanchen/email_operations.git
Author: SkyOceanChen
Author-email: skyoceanchen@foxmail.com
License: MIT
Keywords: basic_type,python
Classifier: Development Status :: 3 - Alpha
Classifier: Intended Audience :: Developers
Classifier: Operating System :: OS Independent
Classifier: Topic :: Software Development :: Build Tools
Classifier: License :: OSI Approved :: MIT License
Classifier: Programming Language :: Python :: 3.6
Classifier: Programming Language :: Python :: 3.8
Classifier: Programming Language :: Python :: 3.10
Requires-Python: >=3
License-File: LICENSE.txt
